Metadata-Version: 2.4
Name: suspect
Version: 0.6.1
Home-page: https://github.com/bennyrowland/suspect.git
Author: bennyrowland
Author-email: bennyrowland@mac.com
License: MIT
Classifier: Development Status :: 4 - Beta
Classifier: Intended Audience :: Science/Research
Classifier: Topic :: Scientific/Engineering :: Medical Science Apps.
Classifier: Topic :: Scientific/Engineering :: Physics
Classifier: License :: OSI Approved :: MIT License
Classifier: Programming Language :: Python :: 3
Classifier: Programming Language :: Python :: 3.8
Classifier: Programming Language :: Python :: 3.9
Classifier: Programming Language :: Python :: 3.10
Classifier: Programming Language :: Python :: 3.11
Classifier: Programming Language :: Python :: 3.12
License-File: LICENSE
Requires-Dist: pywavelets
Requires-Dist: scipy
Requires-Dist: numpy
Requires-Dist: lmfit
Requires-Dist: pydicom
Requires-Dist: parsley
Requires-Dist: parse
Requires-Dist: nibabel
Dynamic: author
Dynamic: author-email
Dynamic: classifier
Dynamic: description
Dynamic: description-content-type
Dynamic: home-page
Dynamic: license
Dynamic: license-file
Dynamic: requires-dist
